pfsense_git_config/__init__.py
pfsense_git_config/git_repo.py
pfsense_git_config/main.py
pfsense_git_config/pfsense_configs.py
pfsense_git_config-1.0.0.dist-info/METADATA
pfsense_git_config-1.0.0.dist-info/WHEEL
pfsense_git_config-1.0.0.dist-info/entry_points.txt
pfsense_git_config-1.0.0.dist-info/RECORD
