Metadata-Version: 2.1
Name: pfsense-git-config
Version: 1.0.0
Summary: pfSense Git Config
Home-page: https://pypi.org/project/pfsense-git-config/
Author: Nigel Metheringham
Author-email: nigel.metheringham@gmail.com
Requires-Python: >=3.11,<4.0
Classifier: Programming Language :: Python :: 3
Classifier: Programming Language :: Python :: 3.11
Requires-Dist: defusedxml (>=0.7.1,<0.8.0)
Requires-Dist: gitpython (>=3.1.31,<4.0.0)
Requires-Dist: loguru (>=0.7.0,<0.8.0)
Requires-Dist: pytz (>=2023.3,<2024.0)
Requires-Dist: pyyaml (>=6.0,<7.0)
Requires-Dist: rich (>=13.4.2,<14.0.0)
Requires-Dist: typer (>=0.9.0,<0.10.0)
Project-URL: Repository, https://github.com/nigelm/pfsense_git_config
